{
  "_fv": 43,
  "_type": "livingentity",
  "definition": {
    "mobName": "Zbboss",
    "mobLabel": "zb Boss",
    "mobModelName": "Biped",
    "mobModelTexture": "yao_feng_.png",
    "mobModelGlowTexture": "",
    "solidBoundingBox": {
      "fixedValue": false
    },
    "modelWidth": 0.6,
    "modelHeight": 1.8,
    "modelShadowSize": 0.6,
    "mountedYOffset": 0.5,
    "hasSpawnEgg": true,
    "spawnEggBaseColor": {
      "value": -11081,
      "falpha": 0.0
    },
    "spawnEggDotColor": {
      "value": -6272502,
      "falpha": 0.0
    },
    "creativeTab": {
      "value": "MISC"
    },
    "isBoss": true,
    "bossBarColor": "RED",
    "bossBarType": "PROGRESS",
    "equipmentMainHand": {
      "value": "Items.NETHERITE_SWORD"
    },
    "equipmentOffHand": {
      "value": "CUSTOM:Zbitem"
    },
    "equipmentHelmet": {
      "value": "Items.NETHERITE_HELMET"
    },
    "equipmentBody": {
      "value": "Items.NETHERITE_CHESTPLATE"
    },
    "equipmentLeggings": {
      "value": "Items.NETHERITE_LEGGINGS"
    },
    "equipmentBoots": {
      "value": "Items.NETHERITE_BOOTS"
    },
    "mobBehaviourType": "Mob",
    "mobCreatureType": "UNDEFINED",
    "attackStrength": 10,
    "attackKnockback": 2.0,
    "knockbackResistance": 1.0,
    "movementSpeed": 1.0,
    "stepHeight": 2.0,
    "armorBaseValue": 20.0,
    "trackingRange": 256,
    "followRange": 128,
    "health": 1000,
    "xpAmount": 10000,
    "waterMob": false,
    "flyingMob": false,
    "guiBoundTo": "<NONE>",
    "inventorySize": 9,
    "inventoryStackSize": 64,
    "disableCollisions": false,
    "ridable": false,
    "canControlForward": false,
    "canControlStrafe": false,
    "immuneToFire": true,
    "immuneToArrows": false,
    "immuneToFallDamage": false,
    "immuneToCactus": false,
    "immuneToDrowning": true,
    "immuneToLightning": false,
    "immuneToPotions": false,
    "immuneToPlayer": false,
    "immuneToExplosion": false,
    "immuneToTrident": false,
    "immuneToAnvil": false,
    "immuneToWither": false,
    "immuneToDragonBreath": false,
    "mobDrop": {
      "value": "CUSTOM:Zbblock"
    },
    "livingSound": {
      "value": ""
    },
    "hurtSound": {
      "value": "entity.generic.hurt"
    },
    "deathSound": {
      "value": "entity.generic.death"
    },
    "stepSound": {
      "value": ""
    },
    "hasAI": true,
    "aiBase": "(none)",
    "aixml": "<xml xmlns=\"https://developers.google.com/blockly/xml\"><block type=\"aitasks_container\" deletable=\"false\" x=\"86\" y=\"41\"><next><block type=\"attack_on_collide\"><field name=\"speed\">1</field><field name=\"longmemory\">TRUE</field><field name=\"condition\">null,null</field><next><block type=\"attack_action\"><field name=\"callhelp\">TRUE</field><field name=\"condition\">null,null</field><next><block type=\"look_around\"><field name=\"condition\">null,null</field><next><block type=\"swim_in_water\"><field name=\"condition\">null,null</field><next><block type=\"leap_at_target\"><field name=\"speed\">1</field><field name=\"condition\">null,null</field><next><block type=\"wander\"><field name=\"speed\">0.5</field><field name=\"condition\">null,null</field><next><block type=\"wander_avoid_water\"><field name=\"speed\">0.5</field><field name=\"condition\">null,null</field><next><block type=\"swim\"><field name=\"speed\">0.25</field><field name=\"condition\">null,null</field><next><block type=\"watch_closest_entity\"><field name=\"radius\">128</field><field name=\"entity\">EntityPlayer</field><field name=\"condition\">null,null</field><next><block type=\"avoid_entity\"><field name=\"radius\">6</field><field name=\"farspeed\">1</field><field name=\"nearspeed\">1.2</field><field name=\"entity\">EntityMinecartTNT</field><field name=\"condition\">null,null</field><next><block type=\"avoid_entity\"><field name=\"radius\">6</field><field name=\"farspeed\">1</field><field name=\"nearspeed\">1.2</field><field name=\"entity\">EntityTNTPrimed</field><field name=\"condition\">null,null</field><next><block type=\"avoid_entity\"><field name=\"radius\">6</field><field name=\"farspeed\">1</field><field name=\"nearspeed\">1.2</field><field name=\"entity\">EntityEnderCrystal</field><field name=\"condition\">null,null</field></block></next></block></next></block></next></block></next></block></next></block></next></block></next></block></next></block></next></block></next></block></next></block></next></block></xml>",
    "breedable": false,
    "tameable": false,
    "breedTriggerItems": [],
    "ranged": false,
    "rangedAttackItem": {
      "value": ""
    },
    "rangedItemType": "Default item",
    "rangedAttackInterval": 20,
    "rangedAttackRadius": 10.0,
    "spawnThisMob": true,
    "doesDespawnWhenIdle": false,
    "spawningProbability": 1,
    "mobSpawningType": "monster",
    "minNumberOfMobsPerGroup": 1,
    "maxNumberOfMobsPerGroup": 1,
    "restrictionBiomes": [
      {
        "value": "deep_dark"
      }
    ],
    "spawnInDungeons": false
  }
}